mcp_server_selenium/__init__.py
mcp_server_selenium/__main__.py
mcp_server_selenium/server.py
mcp_server_selenium/tools/__init__.py
mcp_server_selenium/tools/element_interaction.py
mcp_server_selenium/tools/local_storage.py
mcp_server_selenium/tools/logs.py
mcp_server_selenium/tools/navigate.py
mcp_server_selenium/tools/page_ready.py
mcp_server_selenium/tools/screenshot.py
mcp_server_selenium/tools/script.py
mcp_server_selenium/tools/style.py
mcp_server_selenium-0.1.5.dist-info/METADATA
mcp_server_selenium-0.1.5.dist-info/WHEEL
mcp_server_selenium-0.1.5.dist-info/entry_points.txt
mcp_server_selenium-0.1.5.dist-info/RECORD
