Metadata-Version: 2.4
Name: mcp-server-selenium
Version: 0.1.5
Summary: A Model Context Protocol server for Selenium web automation
Project-URL: Homepage, https://github.com/PhungXuanAnh/selenium-mcp-server
Project-URL: Bug Reports, https://github.com/PhungXuanAnh/selenium-mcp-server/issues
Project-URL: Source Code, https://github.com/PhungXuanAnh/selenium-mcp-server
Project-URL: Documentation, https://github.com/PhungXuanAnh/selenium-mcp-server#readme
Project-URL: Changelog, https://github.com/PhungXuanAnh/selenium-mcp-server/releases
Author-email: PhungXuanAnh <phungxuananh1991@gmail.com>
License: MIT
Requires-Python: >=3.10
Requires-Dist: click
Requires-Dist: mcp[cli]
Requires-Dist: selenium
